sem/CRF.py
sem/__init__.py
sem/__main__.py
sem/annotators.py
sem/constants.py
sem/exporters.py
sem/features.py
sem/gui_components.py
sem/importers.py
sem/logger.py
sem/pipelines.py
sem/processors.py
sem/storage.py
sem/tokenisers.py
sem/util.py
sem/modules/__init__.py
sem/modules/annotate.py
sem/modules/annotation_gui.py
sem/modules/augment_wapiti_model.py
sem/modules/clean.py
sem/modules/download.py
sem/modules/enrich.py
sem/modules/evaluate.py
sem/modules/export.py
sem/modules/gui.py
sem/modules/label_consistency.py
sem/modules/map_annotations.py
sem/modules/pymorphy.py
sem/modules/segmentation.py
sem/modules/tagger.py
sem/modules/wapiti_label.py
sem/modules/workflow_to_pipeline.py
sem/tests/__init__.py
sem/tests/test_features.py
sem/tests/test_processors.py
sem/tests/test_segmentation.py
sem/tests/test_workflows.py
semtagger-4.0.0a2.dist-info/LICENSE
semtagger-4.0.0a2.dist-info/METADATA
semtagger-4.0.0a2.dist-info/WHEEL
semtagger-4.0.0a2.dist-info/entry_points.txt
semtagger-4.0.0a2.dist-info/top_level.txt
semtagger-4.0.0a2.dist-info/RECORD
