Metadata-Version: 2.1
Name: semtagger
Version: 4.0.0a2
Summary: SEM tool for text annotation
Home-page: https://github.com/YoannDupont/SEM
Author: Yoann Dupont
Author-email: yoa.dupont@gmail.com
License: MIT
Project-URL: Bug Tracker, https://github.com/YoannDupont/SEM/issues
Keywords: natural language processing,POS tagging,chunking,named entity recognition
Platform: UNKNOWN
Classifier: Programming Language :: Python :: 3.6
Classifier: Programming Language :: Python :: 3.7
Classifier: License :: OSI Approved :: MIT License
Classifier: Operating System :: OS Independent
Requires-Python: >=3.6
License-File: LICENSE
Requires-Dist: libwapiti
Requires-Dist: dill
Requires-Dist: pymorphy2
Provides-Extra: all
Requires-Dist: pyperclip ; extra == 'all'
Provides-Extra: clipboard
Requires-Dist: pyperclip ; extra == 'clipboard'
